{
  "sourceFile": "PAINEL CABW - RP - MAIO 2026.xlsx",
  "latestReferenceColumn": "MES_ANO REF CONS SISCAB",
  "latestReferenceIso": "2026-05-01",
  "latestReferenceLabel": "Maio/2026",
  "totalRegistros": 435,
  "totalSaldoUsd": 59290713.4,
  "totalOms": 22,
  "totalContratosPag": 147,
  "totalAnosRp": 4,
  "totalEmpenhos": 398,
  "porAno": [
    {
      "label": "2022",
      "saldoUsd": 1180840.73
    },
    {
      "label": "2023",
      "saldoUsd": 366337.61
    },
    {
      "label": "2024",
      "saldoUsd": 1898757.62
    },
    {
      "label": "2025",
      "saldoUsd": 55844777.44
    }
  ],
  "topOms": [
    {
      "label": "PARQUE MATERIAL AER. DO GALEAO",
      "saldoUsd": 21063167.38
    },
    {
      "label": "PARQUE DE MATERIAL AER. DE SAO PAULO",
      "saldoUsd": 15216587.73
    },
    {
      "label": "PARQUE DE MATERIAL AER. LAGOA SANTA",
      "saldoUsd": 12282923.6
    },
    {
      "label": "PARQUE MATERIAL BELICO AER. RJ",
      "saldoUsd": 5041915.88
    },
    {
      "label": "COMISSAO IMPTC. SISTEMA CTR. ESPC.AEREO BRASILEIRO",
      "saldoUsd": 1998992.58
    },
    {
      "label": "DIRETORIA DE MATERIAL AERONAUTICA E BELICO",
      "saldoUsd": 1789632.18
    },
    {
      "label": "COMISSAO AERO. BRASILEIRA EM WASHINGTON",
      "saldoUsd": 1125805.56
    },
    {
      "label": "PARQUE MATERIAL ELET. AERONAUTICA RJ",
      "saldoUsd": 245880.0
    },
    {
      "label": "GABINETE DO COMANDANTE DA AERONAUTICA",
      "saldoUsd": 229218.98
    },
    {
      "label": "DIRETORIA DE SAUDE DA AERONAUTICA",
      "saldoUsd": 125473.35
    }
  ],
  "topContratos": [
    {
      "label": "028/CABW-PAMAGL/2025",
      "saldoUsd": 15600000.0
    },
    {
      "label": "BR-D-KCQ-USAF",
      "saldoUsd": 9736042.14
    },
    {
      "label": "240609",
      "saldoUsd": 4946145.82
    },
    {
      "label": "BR-D-QAQ-USAF",
      "saldoUsd": 4246484.0
    },
    {
      "label": "051/CELOG-PAMASP/2024",
      "saldoUsd": 3817235.9
    },
    {
      "label": "240299",
      "saldoUsd": 2410074.36
    },
    {
      "label": "021/CABW-PAMASP/2025",
      "saldoUsd": 1998961.62
    },
    {
      "label": "190860",
      "saldoUsd": 1646734.92
    },
    {
      "label": "033/CELOG-PAMAGL/2025",
      "saldoUsd": 1495443.27
    },
    {
      "label": "027/CABW-PAMAGL/2025",
      "saldoUsd": 1260000.0
    }
  ],
  "deduplicationPolicy": "O painel utiliza somente os registros da maior referência disponível na coluna MES_ANO REF CONS SISCAB, excluindo saldos históricos não presentes na planilha atual."
}